instagrump
