Metadata-Version: 2.1
Name: instagrump
Version: 1.2.1
Summary: Instagram public API wrapper
Home-page: https://github.com/anandakelvin/instagrump
Author: Kelvin Ananda
Author-email: ananda.kelvin@gmail.com
License: MIT
Keywords: Instagram,wrapper,public,API,scraping
Platform: UNKNOWN
Classifier: Development Status :: 5 - Production/Stable
Classifier: Topic :: Internet
Classifier: License :: OSI Approved :: MIT License
